Metadata-Version: 2.1
Name: lilacai
Version: 0.0.9
Summary: Organize unstructured data
Home-page: https://github.com/lilacai/lilac
License: Apache-2.0
Author: Lilac AI Inc.
Author-email: info@lilacml.com
Requires-Python: >=3.9,<4.0
Classifier: License :: OSI Approved :: Apache Software License
Classifier: Programming Language :: Python :: 3
Classifier: Programming Language :: Python :: 3.9
Classifier: Programming Language :: Python :: 3.10
Classifier: Programming Language :: Python :: 3.11
Provides-Extra: all
Provides-Extra: cohere
Provides-Extra: embeddings
Provides-Extra: gmail
Provides-Extra: gte
Provides-Extra: lang-detection
Provides-Extra: llms
Provides-Extra: ner
Provides-Extra: openai
Provides-Extra: palm
Provides-Extra: pii
Provides-Extra: sbert
Provides-Extra: signals
Provides-Extra: text-stats
Requires-Dist: authlib (>=1.2.1,<2.0.0)
Requires-Dist: click (>=8.1.3,<9.0.0)
Requires-Dist: cohere (>=3.7.0,<4.0.0) ; extra == "all" or extra == "embeddings" or extra == "cohere"
Requires-Dist: dask (>=2023.3.2,<2024.0.0)
Requires-Dist: datasets (>=2.12.0,<3.0.0)
Requires-Dist: detect-secrets (>=1.4.0,<2.0.0) ; extra == "all" or extra == "signals" or extra == "pii"
Requires-Dist: distributed (>=2023.3.2.1,<2024.0.0.0)
Requires-Dist: duckdb (>=0.8.1,<0.9.0)
Requires-Dist: email-reply-parser (>=0.5.12,<0.6.0) ; extra == "all" or extra == "gmail"
Requires-Dist: fastapi (>=0.98.0,<0.99.0)
Requires-Dist: gcsfs (>=2023.4.0,<2024.0.0)
Requires-Dist: google-api-python-client (>=2.88.0,<3.0.0) ; extra == "all" or extra == "gmail"
Requires-Dist: google-auth-httplib2 (>=0.1.0,<0.2.0) ; extra == "all" or extra == "gmail"
Requires-Dist: google-auth-oauthlib (>=1.0.0,<2.0.0) ; extra == "all" or extra == "gmail"
Requires-Dist: google-cloud-storage (>=2.5.0,<3.0.0)
Requires-Dist: google-generativeai (>=0.1.0,<0.2.0) ; extra == "all" or extra == "embeddings" or extra == "palm"
Requires-Dist: gunicorn (>=20.1.0,<21.0.0)
Requires-Dist: hnswlib (>=0.7.0,<0.8.0)
Requires-Dist: httpx (>=0.24.1,<0.25.0)
Requires-Dist: itsdangerous (>=2.1.2,<3.0.0)
Requires-Dist: joblib (>=1.3.1,<2.0.0)
Requires-Dist: langdetect (>=1.0.9,<2.0.0) ; extra == "all" or extra == "signals" or extra == "lang-detection"
Requires-Dist: openai (>=0.27.8,<0.28.0) ; extra == "all" or extra == "embeddings" or extra == "llms" or extra == "openai"
Requires-Dist: openai-function-call (>=0.0.5,<0.0.6)
Requires-Dist: orjson (>=3.8.10,<4.0.0)
Requires-Dist: pillow (>=9.3.0,<10.0.0)
Requires-Dist: psutil (>=5.9.5,<6.0.0)
Requires-Dist: pyarrow (>=9.0.0,<10.0.0)
Requires-Dist: pydantic (>=1.10.11,<2.0.0)
Requires-Dist: python-dotenv (>=1.0.0,<2.0.0)
Requires-Dist: pyyaml (>=6.0.1,<7.0.0)
Requires-Dist: regex (>=2023.6.3,<2024.0.0) ; extra == "pii"
Requires-Dist: requests (>=2,<3)
Requires-Dist: scikit-learn (>=1.3.0,<2.0.0)
Requires-Dist: sentence-transformers (>=2.2.2,<3.0.0) ; extra == "all" or extra == "embeddings" or extra == "gte" or extra == "sbert"
Requires-Dist: spacy (>=3.5.1,<4.0.0) ; extra == "all" or extra == "signals" or extra == "ner" or extra == "text-stats"
Requires-Dist: tenacity (>=8.2.2,<9.0.0)
Requires-Dist: textacy (>=0.13.0,<0.14.0) ; extra == "all" or extra == "signals" or extra == "text-stats"
Requires-Dist: tqdm (>=4.65.0,<5.0.0)
Requires-Dist: types-psutil (>=5.9.5.12,<6.0.0.0)
Requires-Dist: typing-extensions (>=4.7.1,<5.0.0)
Requires-Dist: uvicorn[standard] (>=0.22.0,<0.23.0)
Project-URL: Repository, https://github.com/lilacai/lilac
